cli_arena/__init__.py
cli_arena/__main__.py
cli_arena/canary_protection.py
cli_arena/post_install.py
cli_arena/repository_manager.py
cli_arena/agents/__init__.py
cli_arena/agents/agent_utils.py
cli_arena/agents/base_agent.py
cli_arena/agents/base_docker_agent.py
cli_arena/agents/failure_mode.py
cli_arena/agents/naive_agent.py
cli_arena/agents/oracle_agent.py
cli_arena/agents/prompt_manager.py
cli_arena/agents/simple_oracle_agent.py
cli_arena/agents/installed_agents/naive_agent.py
cli_arena/agents/installed_agents/aider/__init__.py
cli_arena/agents/installed_agents/aider/aider-setup.sh
cli_arena/agents/installed_agents/aider/aider_agent.py
cli_arena/agents/installed_agents/claude_code/__init__.py
cli_arena/agents/installed_agents/claude_code/claude-code-setup.sh
cli_arena/agents/installed_agents/claude_code/claude_code_agent.py
cli_arena/agents/installed_agents/cursor_cli/__init__.py
cli_arena/agents/installed_agents/cursor_cli/cursor_cli_agent.py
cli_arena/agents/installed_agents/gemini_cli/__init__.py
cli_arena/agents/installed_agents/gemini_cli/gemini-cli-setup.sh
cli_arena/agents/installed_agents/gemini_cli/gemini_cli_agent.py
cli_arena/agents/installed_agents/openai_codex/__init__.py
cli_arena/agents/installed_agents/openai_codex/codex-setup.sh
cli_arena/agents/installed_agents/openai_codex/codex_agent.py
cli_arena/agents/prompts/README.md
cli_arena/agents/prompts/USAGE.md
cli_arena/agents/prompts/complex_prompt.txt
cli_arena/agents/prompts/enhanced_multi_step_prompt.txt
cli_arena/agents/prompts/expert_prompt.txt
cli_arena/agents/prompts/my_custom_prompt.txt
cli_arena/agents/prompts/naive_prompt.txt
cli_arena/cache/__init__.py
cli_arena/cache/agent_cache.py
cli_arena/cache/anthropic.py
cli_arena/cli/__init__.py
cli_arena/cli/fork_wizard.py
cli_arena/cli/wizard.py
cli_arena/cli/arena/__init__.py
cli_arena/cli/arena/admin.py
cli_arena/cli/arena/cache.py
cli_arena/cli/arena/datasets.py
cli_arena/cli/arena/docker_cli.py
cli_arena/cli/arena/leaderboard.py
cli_arena-1.2.0.dist-info/METADATA
cli_arena-1.2.0.dist-info/WHEEL
cli_arena-1.2.0.dist-info/entry_points.txt
cli_arena-1.2.0.dist-info/top_level.txt
cli_arena-1.2.0.dist-info/RECORD
